_fastdbf.cp37-win_amd64.pyd
fastdbf/__init__.py
fastdbf/__pycache__/__init__.cpython-37.pyc
fastdbf-0.1.6.dist-info/LICENSE.txt
fastdbf-0.1.6.dist-info/METADATA
fastdbf-0.1.6.dist-info/WHEEL
fastdbf-0.1.6.dist-info/top_level.txt
fastdbf-0.1.6.dist-info/zip-safe
fastdbf-0.1.6.dist-info/RECORD
