Metadata-Version: 2.1
Name: fastdbf
Version: 0.1.6
Summary: Read DBF Files with C and Python, fast.
Home-page: https://pypi.python.org/pypi/fastdbf
Author: Raphael Campestrini
Author-email: rca@seca.at
License: UNKNOWN
Download-URL: https://pypi.python.org/pypi/fastdbf
Project-URL: Source Code, https://github.com/seca-rca/fastdbf
Platform: Windows
Platform: Linux
Platform: Mac OS-X
Platform: Unix
Classifier: Development Status :: 5 - Production/Stable
Classifier: Intended Audience :: Science/Research
Classifier: Intended Audience :: Manufacturing
Classifier: Intended Audience :: Information Technology
Classifier: Intended Audience :: Developers
Classifier: License :: OSI Approved :: The Unlicense (Unlicense)
Classifier: Programming Language :: C
Classifier: Programming Language :: Python
Classifier: Programming Language :: Python :: 3
Classifier: Programming Language :: Python :: 3.6
Classifier: Programming Language :: Python :: 3.7
Classifier: Programming Language :: Python :: 3.8
Classifier: Programming Language :: Python :: 3.9
Classifier: Programming Language :: Python :: 3 :: Only
Classifier: Topic :: Software Development
Classifier: Topic :: Database
Classifier: Topic :: Software Development :: Libraries
Classifier: Operating System :: Microsoft :: Windows :: Windows 10
Classifier: Operating System :: POSIX
Classifier: Operating System :: OS Independent
Classifier: Operating System :: Unix
Classifier: Operating System :: MacOS :: MacOS X
Requires-Python: >=3.6
Requires-Dist: pandas
Requires-Dist: numpy
